MANIFEST.in
setup.py
etc/colab/plugins.d/wikilegis.py
etc/colab/widgets.d/wikilegis_widgets.py
src/colab_wikilegis/__init__.py
src/colab_wikilegis/apps.py
src/colab_wikilegis/data_importer.py
src/colab_wikilegis/diazo.xml
src/colab_wikilegis/models.py
src/colab_wikilegis/search_indexes.py
src/colab_wikilegis/tasks.py
src/colab_wikilegis/urls.py
src/colab_wikilegis/views.py
src/colab_wikilegis.egg-info/PKG-INFO
src/colab_wikilegis.egg-info/SOURCES.txt
src/colab_wikilegis.egg-info/dependency_links.txt
src/colab_wikilegis.egg-info/not-zip-safe
src/colab_wikilegis.egg-info/requires.txt
src/colab_wikilegis.egg-info/top_level.txt
src/colab_wikilegis/management/__init__.py
src/colab_wikilegis/management/commands/__init__.py
src/colab_wikilegis/management/commands/fetch_data_wikilegis.py
src/colab_wikilegis/management/commands/import_wikilegis_users.py
src/colab_wikilegis/migrations/0001_initial.py
src/colab_wikilegis/migrations/0002_auto_20160909_1749.py
src/colab_wikilegis/migrations/0003_auto_20160909_1804.py
src/colab_wikilegis/migrations/0004_wikilegisbill_closing_date.py
src/colab_wikilegis/migrations/0005_auto_20170323_2025.py
src/colab_wikilegis/migrations/0006_wikilegisbill_theme.py
src/colab_wikilegis/migrations/0007_auto_20171108_2016.py
src/colab_wikilegis/migrations/__init__.py
src/colab_wikilegis/static/js/edem-wikilegis-plugin.js
src/colab_wikilegis/static/scss/overrides-wikilegis.scss
src/colab_wikilegis/templates/emails/wikilegis_new_user.html
src/colab_wikilegis/templates/proxy/wikilegis.html
src/colab_wikilegis/templates/search/bill_search_preview.html
src/colab_wikilegis/templates/search/comment_search_preview.html
src/colab_wikilegis/templates/search/segment_search_preview.html
src/colab_wikilegis/templates/search/indexes/colab_wikilegis/wikilegisbill_text.txt
src/colab_wikilegis/templates/search/indexes/colab_wikilegis/wikilegiscomment_text.txt
src/colab_wikilegis/templates/search/indexes/colab_wikilegis/wikilegissegment_text.txt
src/colab_wikilegis/templates/widgets/wikilegis_home_section.html
src/colab_wikilegis/templates/widgets/wikilegis_navigation_links.html
src/colab_wikilegis/widgets/__init__.py
src/colab_wikilegis/widgets/home_section.py
src/colab_wikilegis/widgets/navigation_links.py